Workbook

Sheet Trading Steps
A1: Investment Size | B1: Interest Rate | C1: after 6.28 % profit value | D1: Profit amount | E1: Brokerage plus charges Both Side | F1: Pledge Charges with GST both side | G1: Estimated Interest Charges | H1: Remain Profit | I1: Income Tax | J1: Profit after tax | K1: Self Dividend | L1: Growth Amount after Tax and Dividend | M1: 3 in 1 step
A2: 15000 | B2: 0.0985 | C2: =A2*1.0628 -> 15942 | D2: =C2-A2 -> 942 | E2: =((A2+C2)*0.0012) -> 37.1304 | F2: =(25*2)*1.18 -> 59 | G2: =A2 * (17/30) * 8.5 * (B2 / 365 * 7) -> 136.48322 | H2: =D2-E2-F2-G2 -> 709.38638 | I2: =(H2*0.2)*1.04 -> 147.55237 | J2: =H2-I2 -> 561.83401 | K2: =J2*0.5 -> 280.91701 | L2: =J2-K2 -> 280.91701 | M2: =(A2+A3+A4)/3 -> 15282.817
A3: =A2+L2 -> 15280.917 | B3: =B2 -> 0.0985 | C3: =A3*1.0628 -> 16240.559 | D3: =C3-A3 -> 959.64159 | E3: =((A3+C3)*0.0012) -> 37.825771 | F3: =(25*2)*1.18 -> 59 | G3: =A3 * (17/30) * 8.5 * (B3 / 365 * 7) -> 139.03925 | H3: =D3-E3-F3-G3 -> 723.77657 | I3: =(H3*0.2)*1.04 -> 150.54553 | J3: =H3-I3 -> 573.23104 | K3: =J3*0.5 -> 286.61552 | L3: =J3-K3 -> 286.61552
A4: =A3+L3 -> 15567.533 | B4: =B3 -> 0.0985 | C4: =A4*1.0628 -> 16545.174 | D4: =C4-A4 -> 977.64104 | E4: =((A4+C4)*0.0012) -> 38.535247 | F4: =(25*2)*1.18 -> 59 | G4: =A4 * (17/30) * 8.5 * (B4 / 365 * 7) -> 141.64713 | H4: =D4-E4-F4-G4 -> 738.45867 | I4: =(H4*0.2)*1.04 -> 153.5994 | J4: =H4-I4 -> 584.85926 | K4: =J4*0.5 -> 292.42963 | L4: =J4-K4 -> 292.42963
A5: =A4+L4 -> 15859.962 | B5: =B4 -> 0.0985 | C5: =A5*1.0628 -> 16855.968 | D5: =C5-A5 -> 996.00562 | E5: =((A5+C5)*0.0012) -> 39.259116 | F5: =(25*2)*1.18 -> 59 | G5: =A5 * (17/30) * 8.5 * (B5 / 365 * 7) -> 144.30791 | H5: =D5-E5-F5-G5 -> 753.43859 | I5: =(H5*0.2)*1.04 -> 156.71523 | J5: =H5-I5 -> 596.72337 | K5: =J5*0.5 -> 298.36168 | L5: =J5-K5 -> 298.36168 | M5: =(A5+A6+A7)/3 -> 16160.341
A6: =A5+L5 -> 16158.324 | B6: =B5 -> 0.0985 | C6: =A6*1.0628 -> 17173.067 | D6: =C6-A6 -> 1014.7427 | E6: =((A6+C6)*0.0012) -> 39.997669 | F6: =(25*2)*1.18 -> 59 | G6: =A6 * (17/30) * 8.5 * (B6 / 365 * 7) -> 147.02267 | H6: =D6-E6-F6-G6 -> 768.7224 | I6: =(H6*0.2)*1.04 -> 159.89426 | J6: =H6-I6 -> 608.82814 | K6: =J6*0.5 -> 304.41407 | L6: =J6-K6 -> 304.41407
A7: =A6+L6 -> 16462.738 | B7: =B6 -> 0.0985 | C7: =A7*1.0628 -> 17496.598 | D7: =C7-A7 -> 1033.8599 | E7: =((A7+C7)*0.0012) -> 40.751203 | F7: =(25*2)*1.18 -> 59 | G7: =A7 * (17/30) * 8.5 * (B7 / 365 * 7) -> 149.7925 | H7: =D7-E7-F7-G7 -> 784.31624 | I7: =(H7*0.2)*1.04 -> 163.13778 | J7: =H7-I7 -> 621.17846 | K7: =J7*0.5 -> 310.58923 | L7: =J7-K7 -> 310.58923
A8: =A7+L7 -> 16773.327 | B8: =B7 -> 0.0985 | C8: =A8*1.0628 -> 17826.692 | D8: =C8-A8 -> 1053.3649 | E8: =((A8+C8)*0.0012) -> 41.520023 | F8: =(25*2)*1.18 -> 59 | G8: =A8 * (17/30) * 8.5 * (B8 / 365 * 7) -> 152.61851 | H8: =D8-E8-F8-G8 -> 800.22641 | I8: =(H8*0.2)*1.04 -> 166.44709 | J8: =H8-I8 -> 633.77932 | K8: =J8*0.5 -> 316.88966 | L8: =J8-K8 -> 316.88966 | M8: =(A8+A9+A10)/3 -> 17092.36
A9: =A8+L8 -> 17090.217 | B9: =B8 -> 0.0985 | C9: =A9*1.0628 -> 18163.482 | D9: =C9-A9 -> 1073.2656 | E9: =((A9+C9)*0.0012) -> 42.304439 | F9: =(25*2)*1.18 -> 59 | G9: =A9 * (17/30) * 8.5 * (B9 / 365 * 7) -> 155.50185 | H9: =D9-E9-F9-G9 -> 816.45932 | I9: =(H9*0.2)*1.04 -> 169.82354 | J9: =H9-I9 -> 646.63578 | K9: =J9*0.5 -> 323.31789 | L9: =J9-K9 -> 323.31789
A10: =A9+L9 -> 17413.535 | B10: =B9 -> 0.0985 | C10: =A10*1.0628 -> 18507.105 | D10: =C10-A10 -> 1093.57 | E10: =((A10+C10)*0.0012) -> 43.104767 | F10: =(25*2)*1.18 -> 59 | G10: =A10 * (17/30) * 8.5 * (B10 / 365 * 7) -> 158.44368 | H10: =D10-E10-F10-G10 -> 833.02153 | I10: =(H10*0.2)*1.04 -> 173.26848 | J10: =H10-I10 -> 659.75305 | K10: =J10*0.5 -> 329.87652 | L10: =J10-K10 -> 329.87652
A11: =A10+L10 -> 17743.411 | B11: =B10 -> 0.0985 | C11: =A11*1.0628 -> 18857.697 | D11: =C11-A11 -> 1114.2862 | E11: =((A11+C11)*0.0012) -> 43.92133 | F11: =(25*2)*1.18 -> 59 | G11: =A11 * (17/30) * 8.5 * (B11 / 365 * 7) -> 161.44519 | H11: =D11-E11-F11-G11 -> 849.9197 | I11: =(H11*0.2)*1.04 -> 176.7833 | J11: =H11-I11 -> 673.1364 | K11: =J11*0.5 -> 336.5682 | L11: =J11-K11 -> 336.5682 | M11: =(A11+A12+A13)/3 -> 18082.255
A12: =A11+L11 -> 18079.979 | B12: =B11 -> 0.0985 | C12: =A12*1.0628 -> 19215.402 | D12: =C12-A12 -> 1135.4227 | E12: =((A12+C12)*0.0012) -> 44.754458 | F12: =(25*2)*1.18 -> 59 | G12: =A12 * (17/30) * 8.5 * (B12 / 365 * 7) -> 164.50759 | H12: =D12-E12-F12-G12 -> 867.16066 | I12: =(H12*0.2)*1.04 -> 180.36942 | J12: =H12-I12 -> 686.79125 | K12: =J12*0.5 -> 343.39562 | L12: =J12-K12 -> 343.39562
A13: =A12+L12 -> 18423.375 | B13: =B12 -> 0.0985 | C13: =A13*1.0628 -> 19580.363 | D13: =C13-A13 -> 1156.988 | E13: =((A13+C13)*0.0012) -> 45.604486 | F13: =(25*2)*1.18 -> 59 | G13: =A13 * (17/30) * 8.5 * (B13 / 365 * 7) -> 167.6321 | H13: =D13-E13-F13-G13 -> 884.75136 | I13: =(H13*0.2)*1.04 -> 184.02828 | J13: =H13-I13 -> 700.72308 | K13: =J13*0.5 -> 350.36154 | L13: =J13-K13 -> 350.36154
A14: =A13+L13 -> 18773.737 | B14: =B13 -> 0.0985 | C14: =A14*1.0628 -> 19952.727 | D14: =C14-A14 -> 1178.9907 | E14: =((A14+C14)*0.0012) -> 46.471757 | F14: =(25*2)*1.18 -> 59 | G14: =A14 * (17/30) * 8.5 * (B14 / 365 * 7) -> 170.82 | H14: =D14-E14-F14-G14 -> 902.6989 | I14: =(H14*0.2)*1.04 -> 187.76137 | J14: =H14-I14 -> 714.93753 | K14: =J14*0.5 -> 357.46876 | L14: =J14-K14 -> 357.46876 | M14: =(A14+A15+A16)/3 -> 19133.622
A15: =A14+L14 -> 19131.205 | B15: =B14 -> 0.0985 | C15: =A15*1.0628 -> 20332.645 | D15: =C15-A15 -> 1201.4397 | E15: =((A15+C15)*0.0012) -> 47.35662 | F15: =(25*2)*1.18 -> 59 | G15: =A15 * (17/30) * 8.5 * (B15 / 365 * 7) -> 174.07257 | H15: =D15-E15-F15-G15 -> 921.01051 | I15: =(H15*0.2)*1.04 -> 191.57019 | J15: =H15-I15 -> 729.44032 | K15: =J15*0.5 -> 364.72016 | L15: =J15-K15 -> 364.72016
A16: =A15+L15 -> 19495.926 | B16: =B15 -> 0.0985 | C16: =A16*1.0628 -> 20720.27 | D16: =C16-A16 -> 1224.3441 | E16: =((A16+C16)*0.0012) -> 48.259434 | F16: =(25*2)*1.18 -> 59 | G16: =A16 * (17/30) * 8.5 * (B16 / 365 * 7) -> 177.39111 | H16: =D16-E16-F16-G16 -> 939.69358 | I16: =(H16*0.2)*1.04 -> 195.45626 | J16: =H16-I16 -> 744.23731 | K16: =J16*0.5 -> 372.11866 | L16: =J16-K16 -> 372.11866
A17: =A16+L16 -> 19868.044 | B17: =B16 -> 0.0985 | C17: =A17*1.0628 -> 21115.757 | D17: =C17-A17 -> 1247.7132 | E17: =((A17+C17)*0.0012) -> 49.180562 | F17: =(25*2)*1.18 -> 59 | G17: =A17 * (17/30) * 8.5 * (B17 / 365 * 7) -> 180.77698 | H17: =D17-E17-F17-G17 -> 958.75564 | I17: =(H17*0.2)*1.04 -> 199.42117 | J17: =H17-I17 -> 759.33446 | K17: =J17*0.5 -> 379.66723 | L17: =J17-K17 -> 379.66723 | M17: =(A17+A18+A19)/3 -> 20250.279
A18: =A17+L17 -> 20247.711 | B18: =B17 -> 0.0985 | C18: =A18*1.0628 -> 21519.268 | D18: =C18-A18 -> 1271.5563 | E18: =((A18+C18)*0.0012) -> 50.120375 | F18: =(25*2)*1.18 -> 59 | G18: =A18 * (17/30) * 8.5 * (B18 / 365 * 7) -> 184.23152 | H18: =D18-E18-F18-G18 -> 978.20438 | I18: =(H18*0.2)*1.04 -> 203.46651 | J18: =H18-I18 -> 774.73787 | K18: =J18*0.5 -> 387.36893 | L18: =J18-K18 -> 387.36893
A19: =A18+L18 -> 20635.08 | B19: =B18 -> 0.0985 | C19: =A19*1.0628 -> 21930.963 | D19: =C19-A19 -> 1295.883 | E19: =((A19+C19)*0.0012) -> 51.079252 | F19: =(25*2)*1.18 -> 59 | G19: =A19 * (17/30) * 8.5 * (B19 / 365 * 7) -> 187.75615 | H19: =D19-E19-F19-G19 -> 998.04765 | I19: =(H19*0.2)*1.04 -> 207.59391 | J19: =H19-I19 -> 790.45374 | K19: =J19*0.5 -> 395.22687 | L19: =J19-K19 -> 395.22687
A20: =A19+L19 -> 21030.307 | B20: =B19 -> 0.0985 | C20: =A20*1.0628 -> 22351.01 | D20: =C20-A20 -> 1320.7033 | E20: =((A20+C20)*0.0012) -> 52.057581 | F20: =(25*2)*1.18 -> 59 | G20: =A20 * (17/30) * 8.5 * (B20 / 365 * 7) -> 191.35227 | H20: =D20-E20-F20-G20 -> 1018.2934 | I20: =(H20*0.2)*1.04 -> 211.80504 | J20: =H20-I20 -> 806.48841 | K20: =J20*0.5 -> 403.2442 | L20: =J20-K20 -> 403.2442 | M20: =(A20+A21+A22)/3 -> 21436.278
A21: =A20+L20 -> 21433.551 | B21: =B20 -> 0.0985 | C21: =A21*1.0628 -> 22779.578 | D21: =C21-A21 -> 1346.027 | E21: =((A21+C21)*0.0012) -> 53.055756 | F21: =(25*2)*1.18 -> 59 | G21: =A21 * (17/30) * 8.5 * (B21 / 365 * 7) -> 195.02134 | H21: =D21-E21-F21-G21 -> 1038.9499 | I21: =(H21*0.2)*1.04 -> 216.10159 | J21: =H21-I21 -> 822.84835 | K21: =J21*0.5 -> 411.42417 | L21: =J21-K21 -> 411.42417
A22: =A21+L21 -> 21844.976 | B22: =B21 -> 0.0985 | C22: =A22*1.0628 -> 23216.84 | D22: =C22-A22 -> 1371.8645 | E22: =((A22+C22)*0.0012) -> 54.074179 | F22: =(25*2)*1.18 -> 59 | G22: =A22 * (17/30) * 8.5 * (B22 / 365 * 7) -> 198.76484 | H22: =D22-E22-F22-G22 -> 1060.0254 | I22: =(H22*0.2)*1.04 -> 220.48529 | J22: =H22-I22 -> 839.54015 | K22: =J22*0.5 -> 419.77008 | L22: =J22-K22 -> 419.77008
A23: =A22+L22 -> 22264.746 | B23: =B22 -> 0.0985 | C23: =A23*1.0628 -> 23662.972 | D23: =C23-A23 -> 1398.226 | E23: =((A23+C23)*0.0012) -> 55.113261 | F23: =(25*2)*1.18 -> 59 | G23: =A23 * (17/30) * 8.5 * (B23 / 365 * 7) -> 202.58428 | H23: =D23-E23-F23-G23 -> 1081.5285 | I23: =(H23*0.2)*1.04 -> 224.95793 | J23: =H23-I23 -> 856.57056 | K23: =J23*0.5 -> 428.28528 | L23: =J23-K23 -> 428.28528 | M23: =(A23+A24+A25)/3 -> 22695.927
A24: =A23+L23 -> 22693.031 | B24: =B23 -> 0.0985 | C24: =A24*1.0628 -> 24118.153 | D24: =C24-A24 -> 1425.1223 | E24: =((A24+C24)*0.0012) -> 56.173421 | F24: =(25*2)*1.18 -> 59 | G24: =A24 * (17/30) * 8.5 * (B24 / 365 * 7) -> 206.48119 | H24: =D24-E24-F24-G24 -> 1103.4677 | I24: =(H24*0.2)*1.04 -> 229.52129 | J24: =H24-I24 -> 873.94644 | K24: =J24*0.5 -> 436.97322 | L24: =J24-K24 -> 436.97322
A25: =A24+L24 -> 23130.004 | B25: =B24 -> 0.0985 | C25: =A25*1.0628 -> 24582.568 | D25: =C25-A25 -> 1452.5643 | E25: =((A25+C25)*0.0012) -> 57.255087 | F25: =(25*2)*1.18 -> 59 | G25: =A25 * (17/30) * 8.5 * (B25 / 365 * 7) -> 210.45716 | H25: =D25-E25-F25-G25 -> 1125.852 | I25: =(H25*0.2)*1.04 -> 234.17722 | J25: =H25-I25 -> 891.67479 | K25: =J25*0.5 -> 445.8374 | L25: =J25-K25 -> 445.8374
A26: =A25+L25 -> 23575.842 | B26: =B25 -> 0.0985 | C26: =A26*1.0628 -> 25056.404 | D26: =C26-A26 -> 1480.5628 | E26: =((A26+C26)*0.0012) -> 58.358695 | F26: =(25*2)*1.18 -> 59 | G26: =A26 * (17/30) * 8.5 * (B26 / 365 * 7) -> 214.51378 | H26: =D26-E26-F26-G26 -> 1148.6904 | I26: =(H26*0.2)*1.04 -> 238.9276 | J26: =H26-I26 -> 909.76277 | K26: =J26*0.5 -> 454.88139 | L26: =J26-K26 -> 454.88139 | M26: =(A26+A27+A28)/3 -> 24033.799
A27: =A26+L26 -> 24030.723 | B27: =B26 -> 0.0985 | C27: =A27*1.0628 -> 25539.852 | D27: =C27-A27 -> 1509.1294 | E27: =((A27+C27)*0.0012) -> 59.48469 | F27: =(25*2)*1.18 -> 59 | G27: =A27 * (17/30) * 8.5 * (B27 / 365 * 7) -> 218.6527 | H27: =D27-E27-F27-G27 -> 1171.992 | I27: =(H27*0.2)*1.04 -> 243.77434 | J27: =H27-I27 -> 928.21768 | K27: =J27*0.5 -> 464.10884 | L27: =J27-K27 -> 464.10884
A28: =A27+L27 -> 24494.832 | B28: =B27 -> 0.0985 | C28: =A28*1.0628 -> 26033.107 | D28: =C28-A28 -> 1538.2754 | E28: =((A28+C28)*0.0012) -> 60.633527 | F28: =(25*2)*1.18 -> 59 | G28: =A28 * (17/30) * 8.5 * (B28 / 365 * 7) -> 222.87557 | H28: =D28-E28-F28-G28 -> 1195.7663 | I28: =(H28*0.2)*1.04 -> 248.7194 | J28: =H28-I28 -> 947.04694 | K28: =J28*0.5 -> 473.52347 | L28: =J28-K28 -> 473.52347
A29: =A28+L28 -> 24968.355 | B29: =B28 -> 0.0985 | C29: =A29*1.0628 -> 26536.368 | D29: =C29-A29 -> 1568.0127 | E29: =((A29+C29)*0.0012) -> 61.805668 | F29: =(25*2)*1.18 -> 59 | G29: =A29 * (17/30) * 8.5 * (B29 / 365 * 7) -> 227.1841 | H29: =D29-E29-F29-G29 -> 1220.0229 | I29: =(H29*0.2)*1.04 -> 253.76477 | J29: =H29-I29 -> 966.25817 | K29: =J29*0.5 -> 483.12908 | L29: =J29-K29 -> 483.12908 | M29: =(A29+A30+A31)/3 -> 25454.751
A30: =A29+L29 -> 25451.484 | B30: =B29 -> 0.0985 | C30: =A30*1.0628 -> 27049.838 | D30: =C30-A30 -> 1598.3532 | E30: =((A30+C30)*0.0012) -> 63.001586 | F30: =(25*2)*1.18 -> 59 | G30: =A30 * (17/30) * 8.5 * (B30 / 365 * 7) -> 231.58003 | H30: =D30-E30-F30-G30 -> 1244.7716 | I30: =(H30*0.2)*1.04 -> 258.91249 | J30: =H30-I30 -> 985.8591 | K30: =J30*0.5 -> 492.92955 | L30: =J30-K30 -> 492.92955
A31: =A30+L30 -> 25944.414 | B31: =B30 -> 0.0985 | C31: =A31*1.0628 -> 27573.723 | D31: =C31-A31 -> 1629.3092 | E31: =((A31+C31)*0.0012) -> 64.221764 | F31: =(25*2)*1.18 -> 59 | G31: =A31 * (17/30) * 8.5 * (B31 / 365 * 7) -> 236.06514 | H31: =D31-E31-F31-G31 -> 1270.0223 | I31: =(H31*0.2)*1.04 -> 264.16464 | J31: =H31-I31 -> 1005.8577 | K31: =J31*0.5 -> 502.92883 | L31: =J31-K31 -> 502.92883
A32: =A31+L31 -> 26447.343 | B32: =B31 -> 0.0985 | C32: =A32*1.0628 -> 28108.236 | D32: =C32-A32 -> 1660.8931 | E32: =((A32+C32)*0.0012) -> 65.466694 | F32: =(25*2)*1.18 -> 59 | G32: =A32 * (17/30) * 8.5 * (B32 / 365 * 7) -> 240.64123 | H32: =D32-E32-F32-G32 -> 1295.7852 | I32: =(H32*0.2)*1.04 -> 269.52332 | J32: =H32-I32 -> 1026.2619 | K32: =J32*0.5 -> 513.13094 | L32: =J32-K32 -> 513.13094 | M32: =(A32+A33+A34)/3 -> 26963.943
A33: =A32+L32 -> 26960.474 | B33: =B32 -> 0.0985 | C33: =A33*1.0628 -> 28653.591 | D33: =C33-A33 -> 1693.1177 | E33: =((A33+C33)*0.0012) -> 66.736878 | F33: =(25*2)*1.18 -> 59 | G33: =A33 * (17/30) * 8.5 * (B33 / 365 * 7) -> 245.31015 | H33: =D33-E33-F33-G33 -> 1322.0707 | I33: =(H33*0.2)*1.04 -> 274.99071 | J33: =H33-I33 -> 1047.08 | K33: =J33*0.5 -> 523.54 | L33: =J33-K33 -> 523.54
A34: =A33+L33 -> 27484.014 | B34: =B33 -> 0.0985 | C34: =A34*1.0628 -> 29210.01 | D34: =C34-A34 -> 1725.9961 | E34: =((A34+C34)*0.0012) -> 68.032828 | F34: =(25*2)*1.18 -> 59 | G34: =A34 * (17/30) * 8.5 * (B34 / 365 * 7) -> 250.07378 | H34: =D34-E34-F34-G34 -> 1348.8895 | I34: =(H34*0.2)*1.04 -> 280.56901 | J34: =H34-I34 -> 1068.3204 | K34: =J34*0.5 -> 534.16022 | L34: =J34-K34 -> 534.16022
A35: =A34+L34 -> 28018.174 | B35: =B34 -> 0.0985 | C35: =A35*1.0628 -> 29777.715 | D35: =C35-A35 -> 1759.5413 | E35: =((A35+C35)*0.0012) -> 69.355067 | F35: =(25*2)*1.18 -> 59 | G35: =A35 * (17/30) * 8.5 * (B35 / 365 * 7) -> 254.93404 | H35: =D35-E35-F35-G35 -> 1376.2522 | I35: =(H35*0.2)*1.04 -> 286.26046 | J35: =H35-I35 -> 1089.9918 | K35: =J35*0.5 -> 544.99588 | L35: =J35-K35 -> 544.99588 | M35: =(A35+A36+A37)/3 -> 28566.855
A36: =A35+L35 -> 28563.17 | B36: =B35 -> 0.0985 | C36: =A36*1.0628 -> 30356.937 | D36: =C36-A36 -> 1793.7671 | E36: =((A36+C36)*0.0012) -> 70.704128 | F36: =(25*2)*1.18 -> 59 | G36: =A36 * (17/30) * 8.5 * (B36 / 365 * 7) -> 259.89289 | H36: =D36-E36-F36-G36 -> 1404.17 | I36: =(H36*0.2)*1.04 -> 292.06737 | J36: =H36-I36 -> 1112.1027 | K36: =J36*0.5 -> 556.05134 | L36: =J36-K36 -> 556.05134
A37: =A36+L36 -> 29119.221 | B37: =B36 -> 0.0985 | C37: =A37*1.0628 -> 30947.908 | D37: =C37-A37 -> 1828.6871 | E37: =((A37+C37)*0.0012) -> 72.080555 | F37: =(25*2)*1.18 -> 59 | G37: =A37 * (17/30) * 8.5 * (B37 / 365 * 7) -> 264.95234 | H37: =D37-E37-F37-G37 -> 1432.6542 | I37: =(H37*0.2)*1.04 -> 297.99207 | J37: =H37-I37 -> 1134.6621 | K37: =J37*0.5 -> 567.33106 | L37: =J37-K37 -> 567.33106
A38: =A37+L37 -> 29686.552 | B38: =B37 -> 0.0985 | C38: =A38*1.0628 -> 31550.868 | D38: =C38-A38 -> 1864.3155 | E38: =((A38+C38)*0.0012) -> 73.484904 | F38: =(25*2)*1.18 -> 59 | G38: =A38 * (17/30) * 8.5 * (B38 / 365 * 7) -> 270.11441 | H38: =D38-E38-F38-G38 -> 1461.7162 | I38: =(H38*0.2)*1.04 -> 304.03696 | J38: =H38-I38 -> 1157.6792 | K38: =J38*0.5 -> 578.8396 | L38: =J38-K38 -> 578.8396 | M38: =(A38+A39+A40)/3 -> 30269.306
A39: =A38+L38 -> 30265.392 | B39: =B38 -> 0.0985 | C39: =A39*1.0628 -> 32166.058 | D39: =C39-A39 -> 1900.6666 | E39: =((A39+C39)*0.0012) -> 74.91774 | F39: =(25*2)*1.18 -> 59 | G39: =A39 * (17/30) * 8.5 * (B39 / 365 * 7) -> 275.38121 | H39: =D39-E39-F39-G39 -> 1491.3677 | I39: =(H39*0.2)*1.04 -> 310.20447 | J39: =H39-I39 -> 1181.1632 | K39: =J39*0.5 -> 590.58159 | L39: =J39-K39 -> 590.58159
A40: =A39+L39 -> 30855.973 | B40: =B39 -> 0.0985 | C40: =A40*1.0628 -> 32793.728 | D40: =C40-A40 -> 1937.7551 | E40: =((A40+C40)*0.0012) -> 76.379642 | F40: =(25*2)*1.18 -> 59 | G40: =A40 * (17/30) * 8.5 * (B40 / 365 * 7) -> 280.75484 | H40: =D40-E40-F40-G40 -> 1521.6206 | I40: =(H40*0.2)*1.04 -> 316.49709 | J40: =H40-I40 -> 1205.1236 | K40: =J40*0.5 -> 602.56178 | L40: =J40-K40 -> 602.56178
A41: =A40+L40 -> 31458.535 | B41: =B40 -> 0.0985 | C41: =A41*1.0628 -> 33434.131 | D41: =C41-A41 -> 1975.596 | E41: =((A41+C41)*0.0012) -> 77.871199 | F41: =(25*2)*1.18 -> 59 | G41: =A41 * (17/30) * 8.5 * (B41 / 365 * 7) -> 286.23748 | H41: =D41-E41-F41-G41 -> 1552.4873 | I41: =(H41*0.2)*1.04 -> 322.91736 | J41: =H41-I41 -> 1229.57 | K41: =J41*0.5 -> 614.78498 | L41: =J41-K41 -> 614.78498 | M41: =(A41+A42+A43)/3 -> 32077.477
A42: =A41+L41 -> 32073.32 | B42: =B41 -> 0.0985 | C42: =A42*1.0628 -> 34087.525 | D42: =C42-A42 -> 2014.2045 | E42: =((A42+C42)*0.0012) -> 79.393014 | F42: =(25*2)*1.18 -> 59 | G42: =A42 * (17/30) * 8.5 * (B42 / 365 * 7) -> 291.83133 | H42: =D42-E42-F42-G42 -> 1583.9802 | I42: =(H42*0.2)*1.04 -> 329.46787 | J42: =H42-I42 -> 1254.5123 | K42: =J42*0.5 -> 627.25614 | L42: =J42-K42 -> 627.25614
A43: =A42+L42 -> 32700.576 | B43: =B42 -> 0.0985 | C43: =A43*1.0628 -> 34754.172 | D43: =C43-A43 -> 2053.5962 | E43: =((A43+C43)*0.0012) -> 80.945698 | F43: =(25*2)*1.18 -> 59 | G43: =A43 * (17/30) * 8.5 * (B43 / 365 * 7) -> 297.53866 | H43: =D43-E43-F43-G43 -> 1616.1118 | I43: =(H43*0.2)*1.04 -> 336.15126 | J43: =H43-I43 -> 1279.9606 | K43: =J43*0.5 -> 639.98028 | L43: =J43-K43 -> 639.98028
A44: =A43+L43 -> 33340.557 | B44: =B43 -> 0.0985 | C44: =A44*1.0628 -> 35434.343 | D44: =C44-A44 -> 2093.7869 | E44: =((A44+C44)*0.0012) -> 82.52988 | F44: =(25*2)*1.18 -> 59 | G44: =A44 * (17/30) * 8.5 * (B44 / 365 * 7) -> 303.36177 | H44: =D44-E44-F44-G44 -> 1648.8953 | I44: =(H44*0.2)*1.04 -> 342.97022 | J44: =H44-I44 -> 1305.9251 | K44: =J44*0.5 -> 652.96254 | L44: =J44-K44 -> 652.96254 | M44: =(A44+A45+A46)/3 -> 33997.934
A45: =A44+L44 -> 33993.519 | B45: =B44 -> 0.0985 | C45: =A45*1.0628 -> 36128.312 | D45: =C45-A45 -> 2134.793 | E45: =((A45+C45)*0.0012) -> 84.146197 | F45: =(25*2)*1.18 -> 59 | G45: =A45 * (17/30) * 8.5 * (B45 / 365 * 7) -> 309.30299 | H45: =D45-E45-F45-G45 -> 1682.3438 | I45: =(H45*0.2)*1.04 -> 349.92751 | J45: =H45-I45 -> 1332.4163 | K45: =J45*0.5 -> 666.20815 | L45: =J45-K45 -> 666.20815
A46: =A45+L45 -> 34659.727 | B46: =B45 -> 0.0985 | C46: =A46*1.0628 -> 36836.358 | D46: =C46-A46 -> 2176.6309 | E46: =((A46+C46)*0.0012) -> 85.795302 | F46: =(25*2)*1.18 -> 59 | G46: =A46 * (17/30) * 8.5 * (B46 / 365 * 7) -> 315.36474 | H46: =D46-E46-F46-G46 -> 1716.4708 | I46: =(H46*0.2)*1.04 -> 357.02593 | J46: =H46-I46 -> 1359.4449 | K46: =J46*0.5 -> 679.72245 | L46: =J46-K46 -> 679.72245
A47: =A46+L46 -> 35339.45 | B47: =B46 -> 0.0985 | C47: =A47*1.0628 -> 37558.767 | D47: =C47-A47 -> 2219.3174 | E47: =((A47+C47)*0.0012) -> 87.47786 | F47: =(25*2)*1.18 -> 59 | G47: =A47 * (17/30) * 8.5 * (B47 / 365 * 7) -> 321.54946 | H47: =D47-E47-F47-G47 -> 1751.2901 | I47: =(H47*0.2)*1.04 -> 364.26835 | J47: =H47-I47 -> 1387.0218 | K47: =J47*0.5 -> 693.51089 | L47: =J47-K47 -> 693.51089 | M47: =(A47+A48+A49)/3 -> 36037.65
A48: =A47+L47 -> 36032.961 | B48: =B47 -> 0.0985 | C48: =A48*1.0628 -> 38295.83 | D48: =C48-A48 -> 2262.8699 | E48: =((A48+C48)*0.0012) -> 89.194549 | F48: =(25*2)*1.18 -> 59 | G48: =A48 * (17/30) * 8.5 * (B48 / 365 * 7) -> 327.85963 | H48: =D48-E48-F48-G48 -> 1786.8157 | I48: =(H48*0.2)*1.04 -> 371.65767 | J48: =H48-I48 -> 1415.1581 | K48: =J48*0.5 -> 707.57903 | L48: =J48-K48 -> 707.57903
A49: =A48+L48 -> 36740.54 | B49: =B48 -> 0.0985 | C49: =A49*1.0628 -> 39047.845 | D49: =C49-A49 -> 2307.3059 | E49: =((A49+C49)*0.0012) -> 90.946062 | F49: =(25*2)*1.18 -> 59 | G49: =A49 * (17/30) * 8.5 * (B49 / 365 * 7) -> 334.29781 | H49: =D49-E49-F49-G49 -> 1823.062 | I49: =(H49*0.2)*1.04 -> 379.1969 | J49: =H49-I49 -> 1443.8651 | K49: =J49*0.5 -> 721.93256 | L49: =J49-K49 -> 721.93256
A50: =A49+L49 -> 37462.472 | B50: =B49 -> 0.0985 | C50: =A50*1.0628 -> 39815.115 | D50: =C50-A50 -> 2352.6433 | E50: =((A50+C50)*0.0012) -> 92.733105 | F50: =(25*2)*1.18 -> 59 | G50: =A50 * (17/30) * 8.5 * (B50 / 365 * 7) -> 340.86659 | H50: =D50-E50-F50-G50 -> 1860.0436 | I50: =(H50*0.2)*1.04 -> 386.88906 | J50: =H50-I50 -> 1473.1545 | K50: =J50*0.5 -> 736.57725 | L50: =J50-K50 -> 736.57725 | M50: =(A50+A51+A52)/3 -> 38204.03
A51: =A50+L50 -> 38199.049 | B51: =B50 -> 0.0985 | C51: =A51*1.0628 -> 40597.95 | D51: =C51-A51 -> 2398.9003 | E51: =((A51+C51)*0.0012) -> 94.556399 | F51: =(25*2)*1.18 -> 59 | G51: =A51 * (17/30) * 8.5 * (B51 / 365 * 7) -> 347.56862 | H51: =D51-E51-F51-G51 -> 1897.7753 | I51: =(H51*0.2)*1.04 -> 394.73726 | J51: =H51-I51 -> 1503.038 | K51: =J51*0.5 -> 751.51901 | L51: =J51-K51 -> 751.51901
A52: =A51+L51 -> 38950.568 | B52: =B51 -> 0.0985 | C52: =A52*1.0628 -> 41396.664 | D52: =C52-A52 -> 2446.0957 | E52: =((A52+C52)*0.0012) -> 96.416679 | F52: =(25*2)*1.18 -> 59 | G52: =A52 * (17/30) * 8.5 * (B52 / 365 * 7) -> 354.4066 | H52: =D52-E52-F52-G52 -> 1936.2724 | I52: =(H52*0.2)*1.04 -> 402.74466 | J52: =H52-I52 -> 1533.5278 | K52: =J52*0.5 -> 766.76388 | L52: =J52-K52 -> 766.76388
A53: =A52+L52 -> 39717.332 | B53: =B52 -> 0.0985 | C53: =A53*1.0628 -> 42211.581 | D53: =C53-A53 -> 2494.2485 | E53: =((A53+C53)*0.0012) -> 98.314696 | F53: =(25*2)*1.18 -> 59 | G53: =A53 * (17/30) * 8.5 * (B53 / 365 * 7) -> 361.38329 | H53: =D53-E53-F53-G53 -> 1975.5505 | I53: =(H53*0.2)*1.04 -> 410.9145 | J53: =H53-I53 -> 1564.636 | K53: =J53*0.5 -> 782.31799 | L53: =J53-K53 -> 782.31799 | M53: =(A53+A54+A55)/3 -> 40504.94
A54: =A53+L53 -> 40499.65 | B54: =B53 -> 0.0985 | C54: =A54*1.0628 -> 43043.028 | D54: =C54-A54 -> 2543.378 | E54: =((A54+C54)*0.0012) -> 100.25121 | F54: =(25*2)*1.18 -> 59 | G54: =A54 * (17/30) * 8.5 * (B54 / 365 * 7) -> 368.50151 | H54: =D54-E54-F54-G54 -> 2015.6253 | I54: =(H54*0.2)*1.04 -> 419.25007 | J54: =H54-I54 -> 1596.3752 | K54: =J54*0.5 -> 798.18762 | L54: =J54-K54 -> 798.18762
A55: =A54+L54 -> 41297.838 | B55: =B54 -> 0.0985 | C55: =A55*1.0628 -> 43891.342 | D55: =C55-A55 -> 2593.5042 | E55: =((A55+C55)*0.0012) -> 102.22702 | F55: =(25*2)*1.18 -> 59 | G55: =A55 * (17/30) * 8.5 * (B55 / 365 * 7) -> 375.76412 | H55: =D55-E55-F55-G55 -> 2056.5131 | I55: =(H55*0.2)*1.04 -> 427.75472 | J55: =H55-I55 -> 1628.7584 | K55: =J55*0.5 -> 814.37918 | L55: =J55-K55 -> 814.37918
A56: =A55+L55 -> 42112.217 | B56: =B55 -> 0.0985 | C56: =A56*1.0628 -> 44756.864 | D56: =C56-A56 -> 2644.6472 | E56: =((A56+C56)*0.0012) -> 104.2429 | F56: =(25*2)*1.18 -> 59 | G56: =A56 * (17/30) * 8.5 * (B56 / 365 * 7) -> 383.17406 | H56: =D56-E56-F56-G56 -> 2098.2303 | I56: =(H56*0.2)*1.04 -> 436.4319 | J56: =H56-I56 -> 1661.7984 | K56: =J56*0.5 -> 830.89919 | L56: =J56-K56 -> 830.89919 | M56: =(A56+A57+A58)/3 -> 42948.735
A57: =A56+L56 -> 42943.116 | B57: =B56 -> 0.0985 | C57: =A57*1.0628 -> 45639.944 | D57: =C57-A57 -> 2696.8277 | E57: =((A57+C57)*0.0012) -> 106.29967 | F57: =(25*2)*1.18 -> 59 | G57: =A57 * (17/30) * 8.5 * (B57 / 365 * 7) -> 390.73432 | H57: =D57-E57-F57-G57 -> 2140.7937 | I57: =(H57*0.2)*1.04 -> 445.28509 | J57: =H57-I57 -> 1695.5086 | K57: =J57*0.5 -> 847.75431 | L57: =J57-K57 -> 847.75431
A58: =A57+L57 -> 43790.871 | B58: =B57 -> 0.0985 | C58: =A58*1.0628 -> 46540.937 | D58: =C58-A58 -> 2750.0667 | E58: =((A58+C58)*0.0012) -> 108.39817 | F58: =(25*2)*1.18 -> 59 | G58: =A58 * (17/30) * 8.5 * (B58 / 365 * 7) -> 398.44793 | H58: =D58-E58-F58-G58 -> 2184.2206 | I58: =(H58*0.2)*1.04 -> 454.31788 | J58: =H58-I58 -> 1729.9027 | K58: =J58*0.5 -> 864.95135 | L58: =J58-K58 -> 864.95135
A59: =A58+L58 -> 44655.822 | B59: =B58 -> 0.0985 | C59: =A59*1.0628 -> 47460.208 | D59: =C59-A59 -> 2804.3856 | E59: =((A59+C59)*0.0012) -> 110.53924 | F59: =(25*2)*1.18 -> 59 | G59: =A59 * (17/30) * 8.5 * (B59 / 365 * 7) -> 406.31802 | H59: =D59-E59-F59-G59 -> 2228.5284 | I59: =(H59*0.2)*1.04 -> 463.5339 | J59: =H59-I59 -> 1764.9945 | K59: =J59*0.5 -> 882.49723 | L59: =J59-K59 -> 882.49723 | M59: =(A59+A60+A61)/3 -> 45544.286
A60: =A59+L59 -> 45538.319 | B60: =B59 -> 0.0985 | C60: =A60*1.0628 -> 48398.126 | D60: =C60-A60 -> 2859.8064 | E60: =((A60+C60)*0.0012) -> 112.72373 | F60: =(25*2)*1.18 -> 59 | G60: =A60 * (17/30) * 8.5 * (B60 / 365 * 7) -> 414.34776 | H60: =D60-E60-F60-G60 -> 2273.7349 | I60: =(H60*0.2)*1.04 -> 472.93687 | J60: =H60-I60 -> 1800.7981 | K60: =J60*0.5 -> 900.39904 | L60: =J60-K60 -> 900.39904
A61: =A60+L60 -> 46438.718 | B61: =B60 -> 0.0985 | C61: =A61*1.0628 -> 49355.07 | D61: =C61-A61 -> 2916.3515 | E61: =((A61+C61)*0.0012) -> 114.95255 | F61: =(25*2)*1.18 -> 59 | G61: =A61 * (17/30) * 8.5 * (B61 / 365 * 7) -> 422.54038 | H61: =D61-E61-F61-G61 -> 2319.8586 | I61: =(H61*0.2)*1.04 -> 482.53058 | J61: =H61-I61 -> 1837.328 | K61: =J61*0.5 -> 918.66399 | L61: =J61-K61 -> 918.66399
A62: =A61+L61 -> 47357.382 | B62: =B61 -> 0.0985 | C62: =A62*1.0628 -> 50331.426 | D62: =C62-A62 -> 2974.0436 | E62: =((A62+C62)*0.0012) -> 117.22657 | F62: =(25*2)*1.18 -> 59 | G62: =A62 * (17/30) * 8.5 * (B62 / 365 * 7) -> 430.8992 | H62: =D62-E62-F62-G62 -> 2366.9178 | I62: =(H62*0.2)*1.04 -> 492.31891 | J62: =H62-I62 -> 1874.5989 | K62: =J62*0.5 -> 937.29946 | L62: =J62-K62 -> 937.29946 | M62: =(A62+A63+A64)/3 -> 48301.019
A63: =A62+L62 -> 48294.682 | B63: =B62 -> 0.0985 | C63: =A63*1.0628 -> 51327.588 | D63: =C63-A63 -> 3032.906 | E63: =((A63+C63)*0.0012) -> 119.54672 | F63: =(25*2)*1.18 -> 59 | G63: =A63 * (17/30) * 8.5 * (B63 / 365 * 7) -> 439.42757 | H63: =D63-E63-F63-G63 -> 2414.9317 | I63: =(H63*0.2)*1.04 -> 502.3058 | J63: =H63-I63 -> 1912.6259 | K63: =J63*0.5 -> 956.31296 | L63: =J63-K63 -> 956.31296
A64: =A63+L63 -> 49250.995 | B64: =B63 -> 0.0985 | C64: =A64*1.0628 -> 52343.957 | D64: =C64-A64 -> 3092.9625 | E64: =((A64+C64)*0.0012) -> 121.91394 | F64: =(25*2)*1.18 -> 59 | G64: =A64 * (17/30) * 8.5 * (B64 / 365 * 7) -> 448.12895 | H64: =D64-E64-F64-G64 -> 2463.9196 | I64: =(H64*0.2)*1.04 -> 512.49527 | J64: =H64-I64 -> 1951.4243 | K64: =J64*0.5 -> 975.71215 | L64: =J64-K64 -> 975.71215
A65: =A64+L64 -> 50226.707 | B65: =B64 -> 0.0985 | C65: =A65*1.0628 -> 53380.944 | D65: =C65-A65 -> 3154.2372 | E65: =((A65+C65)*0.0012) -> 124.32918 | F65: =(25*2)*1.18 -> 59 | G65: =A65 * (17/30) * 8.5 * (B65 / 365 * 7) -> 457.00684 | H65: =D65-E65-F65-G65 -> 2513.9012 | I65: =(H65*0.2)*1.04 -> 522.89144 | J65: =H65-I65 -> 1991.0097 | K65: =J65*0.5 -> 995.50486 | L65: =J65-K65 -> 995.50486 | M65: =(A65+A66+A67)/3 -> 51228.943
A66: =A65+L65 -> 51222.212 | B66: =B65 -> 0.0985 | C66: =A66*1.0628 -> 54438.966 | D66: =C66-A66 -> 3216.7549 | E66: =((A66+C66)*0.0012) -> 126.79341 | F66: =(25*2)*1.18 -> 59 | G66: =A66 * (17/30) * 8.5 * (B66 / 365 * 7) -> 466.06482 | H66: =D66-E66-F66-G66 -> 2564.8967 | I66: =(H66*0.2)*1.04 -> 533.4985 | J66: =H66-I66 -> 2031.3981 | K66: =J66*0.5 -> 1015.6991 | L66: =J66-K66 -> 1015.6991
A67: =A66+L66 -> 52237.911 | B67: =B66 -> 0.0985 | C67: =A67*1.0628 -> 55518.451 | D67: =C67-A67 -> 3280.5408 | E67: =((A67+C67)*0.0012) -> 129.30763 | F67: =(25*2)*1.18 -> 59 | G67: =A67 * (17/30) * 8.5 * (B67 / 365 * 7) -> 475.30655 | H67: =D67-E67-F67-G67 -> 2616.9266 | I67: =(H67*0.2)*1.04 -> 544.32073 | J67: =H67-I67 -> 2072.6059 | K67: =J67*0.5 -> 1036.3029 | L67: =J67-K67 -> 1036.3029
A68: =A67+L67 -> 53274.214 | B68: =B67 -> 0.0985 | C68: =A68*1.0628 -> 56619.834 | D68: =C68-A68 -> 3345.6206 | E68: =((A68+C68)*0.0012) -> 131.87286 | F68: =(25*2)*1.18 -> 59 | G68: =A68 * (17/30) * 8.5 * (B68 / 365 * 7) -> 484.73574 | H68: =D68-E68-F68-G68 -> 2670.012 | I68: =(H68*0.2)*1.04 -> 555.3625 | J68: =H68-I68 -> 2114.6495 | K68: =J68*0.5 -> 1057.3248 | L68: =J68-K68 -> 1057.3248 | M68: =(A68+A69+A70)/3 -> 54338.688
A69: =A68+L68 -> 54331.538 | B69: =B68 -> 0.0985 | C69: =A69*1.0628 -> 57743.559 | D69: =C69-A69 -> 3412.0206 | E69: =((A69+C69)*0.0012) -> 134.49012 | F69: =(25*2)*1.18 -> 59 | G69: =A69 * (17/30) * 8.5 * (B69 / 365 * 7) -> 494.35622 | H69: =D69-E69-F69-G69 -> 2724.1743 | I69: =(H69*0.2)*1.04 -> 566.62825 | J69: =H69-I69 -> 2157.546 | K69: =J69*0.5 -> 1078.773 | L69: =J69-K69 -> 1078.773
A70: =A69+L69 -> 55410.311 | B70: =B69 -> 0.0985 | C70: =A70*1.0628 -> 58890.079 | D70: =C70-A70 -> 3479.7676 | E70: =((A70+C70)*0.0012) -> 137.16047 | F70: =(25*2)*1.18 -> 59 | G70: =A70 * (17/30) * 8.5 * (B70 / 365 * 7) -> 504.17184 | H70: =D70-E70-F70-G70 -> 2779.4352 | I70: =(H70*0.2)*1.04 -> 578.12253 | J70: =H70-I70 -> 2201.3127 | K70: =J70*0.5 -> 1100.6564 | L70: =J70-K70 -> 1100.6564
A71: =A70+L70 -> 56510.968 | B71: =B70 -> 0.0985 | C71: =A71*1.0628 -> 60059.857 | D71: =C71-A71 -> 3548.8888 | E71: =((A71+C71)*0.0012) -> 139.88499 | F71: =(25*2)*1.18 -> 59 | G71: =A71 * (17/30) * 8.5 * (B71 / 365 * 7) -> 514.18659 | H71: =D71-E71-F71-G71 -> 2835.8172 | I71: =(H71*0.2)*1.04 -> 589.84998 | J71: =H71-I71 -> 2245.9672 | K71: =J71*0.5 -> 1122.9836 | L71: =J71-K71 -> 1122.9836 | M71: =(A71+A72+A73)/3 -> 57641.545
A72: =A71+L71 -> 57633.951 | B72: =B71 -> 0.0985 | C72: =A72*1.0628 -> 61253.364 | D72: =C72-A72 -> 3619.4121 | E72: =((A72+C72)*0.0012) -> 142.66478 | F72: =(25*2)*1.18 -> 59 | G72: =A72 * (17/30) * 8.5 * (B72 / 365 * 7) -> 524.40448 | H72: =D72-E72-F72-G72 -> 2893.3429 | I72: =(H72*0.2)*1.04 -> 601.81532 | J72: =H72-I72 -> 2291.5276 | K72: =J72*0.5 -> 1145.7638 | L72: =J72-K72 -> 1145.7638
A73: =A72+L72 -> 58779.715 | B73: =B72 -> 0.0985 | C73: =A73*1.0628 -> 62471.081 | D73: =C73-A73 -> 3691.3661 | E73: =((A73+C73)*0.0012) -> 145.50096 | F73: =(25*2)*1.18 -> 59 | G73: =A73 * (17/30) * 8.5 * (B73 / 365 * 7) -> 534.82965 | H73: =D73-E73-F73-G73 -> 2952.0355 | I73: =(H73*0.2)*1.04 -> 614.02339 | J73: =H73-I73 -> 2338.0121 | K73: =J73*0.5 -> 1169.0061 | L73: =J73-K73 -> 1169.0061
A74: =A73+L73 -> 59948.721 | B74: =B73 -> 0.0985 | C74: =A74*1.0628 -> 63713.501 | D74: =C74-A74 -> 3764.7797 | E74: =((A74+C74)*0.0012) -> 148.39467 | F74: =(25*2)*1.18 -> 59 | G74: =A74 * (17/30) * 8.5 * (B74 / 365 * 7) -> 545.4663 | H74: =D74-E74-F74-G74 -> 3011.9187 | I74: =(H74*0.2)*1.04 -> 626.4791 | J74: =H74-I74 -> 2385.4396 | K74: =J74*0.5 -> 1192.7198 | L74: =J74-K74 -> 1192.7198 | M74: =(A74+A75+A76)/3 -> 61149.506
A75: =A74+L74 -> 61141.441 | B75: =B74 -> 0.0985 | C75: =A75*1.0628 -> 64981.124 | D75: =C75-A75 -> 3839.6825 | E75: =((A75+C75)*0.0012) -> 151.34708 | F75: =(25*2)*1.18 -> 59 | G75: =A75 * (17/30) * 8.5 * (B75 / 365 * 7) -> 556.31871 | H75: =D75-E75-F75-G75 -> 3073.0167 | I75: =(H75*0.2)*1.04 -> 639.18747 | J75: =H75-I75 -> 2433.8292 | K75: =J75*0.5 -> 1216.9146 | L75: =J75-K75 -> 1216.9146
A76: =A75+L75 -> 62358.356 | B76: =B75 -> 0.0985 | C76: =A76*1.0628 -> 66274.46 | D76: =C76-A76 -> 3916.1047 | E76: =((A76+C76)*0.0012) -> 154.35938 | F76: =(25*2)*1.18 -> 59 | G76: =A76 * (17/30) * 8.5 * (B76 / 365 * 7) -> 567.39127 | H76: =D76-E76-F76-G76 -> 3135.3541 | I76: =(H76*0.2)*1.04 -> 652.15365 | J76: =H76-I76 -> 2483.2004 | K76: =J76*0.5 -> 1241.6002 | L76: =J76-K76 -> 1241.6002
A77: =A76+L76 -> 63599.956 | B77: =B76 -> 0.0985 | C77: =A77*1.0628 -> 67594.033 | D77: =C77-A77 -> 3994.0772 | E77: =((A77+C77)*0.0012) -> 157.43279 | F77: =(25*2)*1.18 -> 59 | G77: =A77 * (17/30) * 8.5 * (B77 / 365 * 7) -> 578.68845 | H77: =D77-E77-F77-G77 -> 3198.956 | I77: =(H77*0.2)*1.04 -> 665.38285 | J77: =H77-I77 -> 2533.5731 | K77: =J77*0.5 -> 1266.7866 | L77: =J77-K77 -> 1266.7866 | M77: =(A77+A78+A79)/3 -> 64875.308
A78: =A77+L77 -> 64866.742 | B78: =B77 -> 0.0985 | C78: =A78*1.0628 -> 68940.374 | D78: =C78-A78 -> 4073.6314 | E78: =((A78+C78)*0.0012) -> 160.56854 | F78: =(25*2)*1.18 -> 59 | G78: =A78 * (17/30) * 8.5 * (B78 / 365 * 7) -> 590.21479 | H78: =D78-E78-F78-G78 -> 3263.8481 | I78: =(H78*0.2)*1.04 -> 678.8804 | J78: =H78-I78 -> 2584.9677 | K78: =J78*0.5 -> 1292.4838 | L78: =J78-K78 -> 1292.4838
A79: =A78+L78 -> 66159.226 | B79: =B78 -> 0.0985 | C79: =A79*1.0628 -> 70314.026 | D79: =C79-A79 -> 4154.7994 | E79: =((A79+C79)*0.0012) -> 163.7679 | F79: =(25*2)*1.18 -> 59 | G79: =A79 * (17/30) * 8.5 * (B79 / 365 * 7) -> 601.97495 | H79: =D79-E79-F79-G79 -> 3330.0566 | I79: =(H79*0.2)*1.04 -> 692.65176 | J79: =H79-I79 -> 2637.4048 | K79: =J79*0.5 -> 1318.7024 | L79: =J79-K79 -> 1318.7024
A80: =A79+L79 -> 67477.929 | B80: =B79 -> 0.0985 | C80: =A80*1.0628 -> 71715.543 | D80: =C80-A80 -> 4237.6139 | E80: =((A80+C80)*0.0012) -> 167.03217 | F80: =(25*2)*1.18 -> 59 | G80: =A80 * (17/30) * 8.5 * (B80 / 365 * 7) -> 613.97366 | H80: =D80-E80-F80-G80 -> 3397.6081 | I80: =(H80*0.2)*1.04 -> 706.70248 | J80: =H80-I80 -> 2690.9056 | K80: =J80*0.5 -> 1345.4528 | L80: =J80-K80 -> 1345.4528 | M80: =(A80+A81+A82)/3 -> 68832.479
A81: =A80+L80 -> 68823.381 | B81: =B80 -> 0.0985 | C81: =A81*1.0628 -> 73145.49 | D81: =C81-A81 -> 4322.1084 | E81: =((A81+C81)*0.0012) -> 170.36265 | F81: =(25*2)*1.18 -> 59 | G81: =A81 * (17/30) * 8.5 * (B81 / 365 * 7) -> 626.21578 | H81: =D81-E81-F81-G81 -> 3466.5299 | I81: =(H81*0.2)*1.04 -> 721.03823 | J81: =H81-I81 -> 2745.4917 | K81: =J81*0.5 -> 1372.7459 | L81: =J81-K81 -> 1372.7459
A82: =A81+L81 -> 70196.127 | B82: =B81 -> 0.0985 | C82: =A82*1.0628 -> 74604.444 | D82: =C82-A82 -> 4408.3168 | E82: =((A82+C82)*0.0012) -> 173.76069 | F82: =(25*2)*1.18 -> 59 | G82: =A82 * (17/30) * 8.5 * (B82 / 365 * 7) -> 638.70623 | H82: =D82-E82-F82-G82 -> 3536.8499 | I82: =(H82*0.2)*1.04 -> 735.66478 | J82: =H82-I82 -> 2801.1851 | K82: =J82*0.5 -> 1400.5926 | L82: =J82-K82 -> 1400.5926
A83: =A82+L82 -> 71596.72 | B83: =B82 -> 0.0985 | C83: =A83*1.0628 -> 76092.994 | D83: =C83-A83 -> 4496.274 | E83: =((A83+C83)*0.0012) -> 177.22766 | F83: =(25*2)*1.18 -> 59 | G83: =A83 * (17/30) * 8.5 * (B83 / 365 * 7) -> 651.45005 | H83: =D83-E83-F83-G83 -> 3608.5963 | I83: =(H83*0.2)*1.04 -> 750.58803 | J83: =H83-I83 -> 2858.0083 | K83: =J83*0.5 -> 1429.0041 | L83: =J83-K83 -> 1429.0041 | M83: =(A83+A84+A85)/3 -> 73035.387
A84: =A83+L83 -> 73025.724 | B84: =B83 -> 0.0985 | C84: =A84*1.0628 -> 77611.739 | D84: =C84-A84 -> 4586.0155 | E84: =((A84+C84)*0.0012) -> 180.76496 | F84: =(25*2)*1.18 -> 59 | G84: =A84 * (17/30) * 8.5 * (B84 / 365 * 7) -> 664.45239 | H84: =D84-E84-F84-G84 -> 3681.7981 | I84: =(H84*0.2)*1.04 -> 765.81401 | J84: =H84-I84 -> 2915.9841 | K84: =J84*0.5 -> 1457.9921 | L84: =J84-K84 -> 1457.9921
A85: =A84+L84 -> 74483.716 | B85: =B84 -> 0.0985 | C85: =A85*1.0628 -> 79161.293 | D85: =C85-A85 -> 4677.5774 | E85: =((A85+C85)*0.0012) -> 184.37401 | F85: =(25*2)*1.18 -> 59 | G85: =A85 * (17/30) * 8.5 * (B85 / 365 * 7) -> 677.71849 | H85: =D85-E85-F85-G85 -> 3756.4849 | I85: =(H85*0.2)*1.04 -> 781.34885 | J85: =H85-I85 -> 2975.136 | K85: =J85*0.5 -> 1487.568 | L85: =J85-K85 -> 1487.568
A86: =A85+L85 -> 75971.284 | B86: =B85 -> 0.0985 | C86: =A86*1.0628 -> 80742.281 | D86: =C86-A86 -> 4770.9966 | E86: =((A86+C86)*0.0012) -> 188.05628 | F86: =(25*2)*1.18 -> 59 | G86: =A86 * (17/30) * 8.5 * (B86 / 365 * 7) -> 691.25369 | H86: =D86-E86-F86-G86 -> 3832.6867 | I86: =(H86*0.2)*1.04 -> 797.19883 | J86: =H86-I86 -> 3035.4878 | K86: =J86*0.5 -> 1517.7439 | L86: =J86-K86 -> 1517.7439 | M86: =(A86+A87+A88)/3 -> 77499.291
A87: =A86+L86 -> 77489.028 | B87: =B86 -> 0.0985 | C87: =A87*1.0628 -> 82355.339 | D87: =C87-A87 -> 4866.311 | E87: =((A87+C87)*0.0012) -> 191.81324 | F87: =(25*2)*1.18 -> 59 | G87: =A87 * (17/30) * 8.5 * (B87 / 365 * 7) -> 705.06347 | H87: =D87-E87-F87-G87 -> 3910.4343 | I87: =(H87*0.2)*1.04 -> 813.37032 | J87: =H87-I87 -> 3097.0639 | K87: =J87*0.5 -> 1548.532 | L87: =J87-K87 -> 1548.532
A88: =A87+L87 -> 79037.56 | B88: =B87 -> 0.0985 | C88: =A88*1.0628 -> 84001.119 | D88: =C88-A88 -> 4963.5588 | E88: =((A88+C88)*0.0012) -> 195.64641 | F88: =(25*2)*1.18 -> 59 | G88: =A88 * (17/30) * 8.5 * (B88 / 365 * 7) -> 719.15337 | H88: =D88-E88-F88-G88 -> 3989.759 | I88: =(H88*0.2)*1.04 -> 829.86987 | J88: =H88-I88 -> 3159.8891 | K88: =J88*0.5 -> 1579.9446 | L88: =J88-K88 -> 1579.9446
A89: =A88+L88 -> 80617.505 | B89: =B88 -> 0.0985 | C89: =A89*1.0628 -> 85680.284 | D89: =C89-A89 -> 5062.7793 | E89: =((A89+C89)*0.0012) -> 199.55735 | F89: =(25*2)*1.18 -> 59 | G89: =A89 * (17/30) * 8.5 * (B89 / 365 * 7) -> 733.5291 | H89: =D89-E89-F89-G89 -> 4070.6928 | I89: =(H89*0.2)*1.04 -> 846.70411 | J89: =H89-I89 -> 3223.9887 | K89: =J89*0.5 -> 1611.9944 | L89: =J89-K89 -> 1611.9944 | M89: =(A89+A90+A91)/3 -> 82240.399
A90: =A89+L89 -> 82229.499 | B90: =B89 -> 0.0985 | C90: =A90*1.0628 -> 87393.511 | D90: =C90-A90 -> 5164.0125 | E90: =((A90+C90)*0.0012) -> 203.54761 | F90: =(25*2)*1.18 -> 59 | G90: =A90 * (17/30) * 8.5 * (B90 / 365 * 7) -> 748.19645 | H90: =D90-E90-F90-G90 -> 4153.2685 | I90: =(H90*0.2)*1.04 -> 863.87984 | J90: =H90-I90 -> 3289.3886 | K90: =J90*0.5 -> 1644.6943 | L90: =J90-K90 -> 1644.6943
A91: =A90+L90 -> 83874.193 | B91: =B90 -> 0.0985 | C91: =A91*1.0628 -> 89141.493 | D91: =C91-A91 -> 5267.2993 | E91: =((A91+C91)*0.0012) -> 207.61882 | F91: =(25*2)*1.18 -> 59 | G91: =A91 * (17/30) * 8.5 * (B91 / 365 * 7) -> 763.16133 | H91: =D91-E91-F91-G91 -> 4237.5192 | I91: =(H91*0.2)*1.04 -> 881.40399 | J91: =H91-I91 -> 3356.1152 | K91: =J91*0.5 -> 1678.0576 | L91: =J91-K91 -> 1678.0576
A92: =A91+L91 -> 85552.251 | B92: =B91 -> 0.0985 | C92: =A92*1.0628 -> 90924.932 | D92: =C92-A92 -> 5372.6813 | E92: =((A92+C92)*0.0012) -> 211.77262 | F92: =(25*2)*1.18 -> 59 | G92: =A92 * (17/30) * 8.5 * (B92 / 365 * 7) -> 778.42977 | H92: =D92-E92-F92-G92 -> 4323.479 | I92: =(H92*0.2)*1.04 -> 899.28362 | J92: =H92-I92 -> 3424.1953 | K92: =J92*0.5 -> 1712.0977 | L92: =J92-K92 -> 1712.0977 | M92: =(A92+A93+A94)/3 -> 87275.925
A93: =A92+L92 -> 87264.348 | B93: =B92 -> 0.0985 | C93: =A93*1.0628 -> 92744.55 | D93: =C93-A93 -> 5480.2011 | E93: =((A93+C93)*0.0012) -> 216.01068 | F93: =(25*2)*1.18 -> 59 | G93: =A93 * (17/30) * 8.5 * (B93 / 365 * 7) -> 794.00795 | H93: =D93-E93-F93-G93 -> 4411.1825 | I93: =(H93*0.2)*1.04 -> 917.52595 | J93: =H93-I93 -> 3493.6565 | K93: =J93*0.5 -> 1746.8283 | L93: =J93-K93 -> 1746.8283
A94: =A93+L93 -> 89011.177 | B94: =B93 -> 0.0985 | C94: =A94*1.0628 -> 94601.079 | D94: =C94-A94 -> 5589.9019 | E94: =((A94+C94)*0.0012) -> 220.33471 | F94: =(25*2)*1.18 -> 59 | G94: =A94 * (17/30) * 8.5 * (B94 / 365 * 7) -> 809.90213 | H94: =D94-E94-F94-G94 -> 4500.6651 | I94: =(H94*0.2)*1.04 -> 936.13833 | J94: =H94-I94 -> 3564.5267 | K94: =J94*0.5 -> 1782.2634 | L94: =J94-K94 -> 1782.2634
A95: =A94+L94 -> 90793.44 | B95: =B94 -> 0.0985 | C95: =A95*1.0628 -> 96495.268 | D95: =C95-A95 -> 5701.828 | E95: =((A95+C95)*0.0012) -> 224.74645 | F95: =(25*2)*1.18 -> 59 | G95: =A95 * (17/30) * 8.5 * (B95 / 365 * 7) -> 826.11873 | H95: =D95-E95-F95-G95 -> 4591.9629 | I95: =(H95*0.2)*1.04 -> 955.12827 | J95: =H95-I95 -> 3636.8346 | K95: =J95*0.5 -> 1818.4173 | L95: =J95-K95 -> 1818.4173 | M95: =(A95+A96+A97)/3 -> 92624.153
A96: =A95+L95 -> 92611.857 | B96: =B95 -> 0.0985 | C96: =A96*1.0628 -> 98427.882 | D96: =C96-A96 -> 5816.0246 | E96: =((A96+C96)*0.0012) -> 229.24769 | F96: =(25*2)*1.18 -> 59 | G96: =A96 * (17/30) * 8.5 * (B96 / 365 * 7) -> 842.6643 | H96: =D96-E96-F96-G96 -> 4685.1127 | I96: =(H96*0.2)*1.04 -> 974.50343 | J96: =H96-I96 -> 3710.6092 | K96: =J96*0.5 -> 1855.3046 | L96: =J96-K96 -> 1855.3046
A97: =A96+L96 -> 94467.162 | B97: =B96 -> 0.0985 | C97: =A97*1.0628 -> 100399.7 | D97: =C97-A97 -> 5932.5378 | E97: =((A97+C97)*0.0012) -> 233.84023 | F97: =(25*2)*1.18 -> 59 | G97: =A97 * (17/30) * 8.5 * (B97 / 365 * 7) -> 859.54549 | H97: =D97-E97-F97-G97 -> 4780.152 | I97: =(H97*0.2)*1.04 -> 994.27163 | J97: =H97-I97 -> 3785.8804 | K97: =J97*0.5 -> 1892.9402 | L97: =J97-K97 -> 1892.9402
A98: =A97+L97 -> 96360.102 | B98: =B97 -> 0.0985 | C98: =A98*1.0628 -> 102411.52 | D98: =C98-A98 -> 6051.4144 | E98: =((A98+C98)*0.0012) -> 238.52594 | F98: =(25*2)*1.18 -> 59 | G98: =A98 * (17/30) * 8.5 * (B98 / 365 * 7) -> 876.76913 | H98: =D98-E98-F98-G98 -> 4877.1193 | I98: =(H98*0.2)*1.04 -> 1014.4408 | J98: =H98-I98 -> 3862.6785 | K98: =J98*0.5 -> 1931.3393 | L98: =J98-K98 -> 1931.3393 | M98: =(A98+A99+A100)/3 -> 98304.501
A99: =A98+L98 -> 98291.441 | B99: =B98 -> 0.0985 | C99: =A99*1.0628 -> 104464.14 | D99: =C99-A99 -> 6172.7025 | E99: =((A99+C99)*0.0012) -> 243.3067 | F99: =(25*2)*1.18 -> 59 | G99: =A99 * (17/30) * 8.5 * (B99 / 365 * 7) -> 894.34216 | H99: =D99-E99-F99-G99 -> 4976.0537 | I99: =(H99*0.2)*1.04 -> 1035.0192 | J99: =H99-I99 -> 3941.0345 | K99: =J99*0.5 -> 1970.5173 | L99: =J99-K99 -> 1970.5173
A100: =A99+L99 -> 100261.96 | B100: =B99 -> 0.0985 | C100: =A100*1.0628 -> 106558.41 | D100: =C100-A100 -> 6296.451 | E100: =((A100+C100)*0.0012) -> 248.18444 | F100: =(25*2)*1.18 -> 59 | G100: =A100 * (17/30) * 8.5 * (B100 / 365 * 7) -> 912.27166 | H100: =D100-E100-F100-G100 -> 5076.9949 | I100: =(H100*0.2)*1.04 -> 1056.0149 | J100: =H100-I100 -> 4020.98 | K100: =J100*0.5 -> 2010.49 | L100: =J100-K100 -> 2010.49
...

Sheet Force and Reserve Force
B1: 1 | E1: 2 | H1: 3 | K1: 4 | N1: 5 | Q1: 6 | T1: 7 | W1: 8 | Z1: 9 | AC1: 10 | AF1: 11 | AI1: 12 | AL1: 13 | AO1: 14 | AR1: 15 | AU1: 16 | AX1: 17
A2: Step | B2: Amount | C2: Stock | D2: F/RF | E2: Amount | F2: Stock | G2: F/RF | H2: Amount | I2: Stock | J2: F/RF | K2: Amount | L2: Stock | M2: F/RF | N2: Amount | O2: Stock | P2: F/RF | Q2: Amount | R2: Stock | S2: F/RF | T2: Amount | U2: Stock | V2: F/RF | W2: Amount | X2: Stock | Y2: F/RF
A3: 1 | B3: ='Trading Steps'!M2 -> 15282.817 | C3: ONGC | D3: F | E3: =B3 -> 15282.817 | F3: BEL | G3: F | H3: =E3 -> 15282.817 | I3: MAHABANK | J3: F
A4: 2 | B4: ='Trading Steps'!M5 -> 16160.341 | C4: POWERGRID | D4: RF | E4: =B4 -> 16160.341 | F4: PETRONET | G4: F | H4: =E4 -> 16160.341 | I4: NLC INDIA | J4: F | K4: =H4 -> 16160.341 | L4: PFC | M4: F | N4: =K4 -> 16160.341 | O4: Apolo Hospital | P4: RF | Q4: =N4 -> 16160.341 | R4: Torrent Power | S4: RF | T4: =Q4 -> 16160.341 | U4: Sun Pharma | V4: RF | W4: =T4 -> 16160.341 | X4: IRB INFRA | Y4: RF
A5: 3 | B5: ='Trading Steps'!M8 -> 17092.36 | C5: NHPC | D5: RF | E5: =B5 -> 17092.36 | F5: HUDCO | G5: F | H5: =E5 -> 17092.36 | I5: GICRE | J5: RF | K5: =H5 -> 17092.36 | L5: NYKAA | M5: RF | N5: =K5 -> 17092.36 | O5: YES BANK | P5: F | Q5: =N5 -> 17092.36 | R5: ATGL | S5: F
A6: 4 | B6: ='Trading Steps'!M11 -> 18082.255 | C6: PREMIRENE | D6: F | E6: =B6 -> 18082.255 | F6: MOTILALOFS | G6: F | H6: =E6 -> 18082.255 | I6: Dr Reddy | J6: RF | K6: =H6 -> 18082.255 | L6: ASIAN PAINT | M6: RF | N6: =K6 -> 18082.255 | O6: SUZLON | P6: RF | Q6: =N6 -> 18082.255 | R6: TMPV | S6: RF | T6: =Q6 -> 18082.255 | U6: FORTIES | V6: RF | W6: =T6 -> 18082.255 | X6: MANKIND | Y6: F
A7: 5 | B7: ='Trading Steps'!M14 -> 19133.622 | C7: IDFCFRSTB | D7: F | E7: =B7 -> 19133.622 | F7: AXISBANK | G7: RF | H7: =E7 -> 19133.622 | I7: Gail | J7: RF | K7: =H7 -> 19133.622 | L7: INDHOTEL | M7: RF | N7: =K7 -> 19133.622 | O7: HUDCO | P7: RF | Q7: =N7 -> 19133.622 | R7: ETERNAL | S7: RF | T7: =Q7 -> 19133.622 | U7: REC Ltd | V7: RF | W7: =T7 -> 19133.622 | X7: BAJAJFIN | Y7: RF | Z7: =W7 -> 19133.622 | AA7: MAXHEALTH | AB7: RF | AC7: =Z7 -> 19133.622 | AD7: LIC | AE7: RF | AF7: =AC7 -> 19133.622 | AG7: HDFCAMC | AH7: RF | AI7: =AF7 -> 19133.622 | AJ7: ENDURANCE | AK7: RF | AL7: =AI7 -> 19133.622 | AM7: 360ONE | AN7: RF | AO7: =AL7 -> 19133.622 | AP7: TVSMOTOR | AQ7: F | AR7: =AO7 -> 19133.622 | AS7: ALKEM | AT7: RF | AU7: =AR7 -> 19133.622 | AV7: HAL | AW7: RF | AX7: =AU7 -> 19133.622 | AY7: COFORGE | AZ7: F
A8: 6 | B8: ='Trading Steps'!M17 -> 20250.279 | C8: EICHERMOT | E8: =B8 -> 20250.279 | F8: SCHAEFFLER | H8: =E8 -> 20250.279 | I8: PRESTIGE
